pbose/__init__.py
pbose/exceptions.py
pbose/core/PbWA.py
pbose/core/PbWE.py
pbose/core/PbWK.py
pbose/core/PbWS.py
pbose/core/PbWT.py
pbose/core/__init__.py
pbose/protobuf/PbWA_pb2.py
pbose/protobuf/PbWE_pb2.py
pbose/protobuf/PbWK_pb2.py
pbose/protobuf/PbWS_pb2.py
pbose/protobuf/PbWT_pb2.py
pbose/protobuf/__init__.py
tests/__init__.py
tests/conftest.py
tests/test_pbwk.py
tests/test_pbws.py
tests/fixtures/__init__.py
tests/fixtures/pbwk.py
pbose-0.3.0.dist-info/LICENSE.txt
pbose-0.3.0.dist-info/METADATA
pbose-0.3.0.dist-info/WHEEL
pbose-0.3.0.dist-info/top_level.txt
pbose-0.3.0.dist-info/RECORD
