Metadata-Version: 2.1
Name: pbose
Version: 0.3.0
Summary: Protobuf Object Signing and Encryption.
Home-page: https://pbose.io
Author: PbOSE
Author-email: UNKNOWN
License: UNKNOWN
Platform: UNKNOWN
Classifier: Development Status :: 2 - Pre-Alpha
Classifier: Programming Language :: Python
Classifier: Programming Language :: Python :: 2
Classifier: Programming Language :: Python :: 2.7
Classifier: Programming Language :: Python :: 3
Classifier: Programming Language :: Python :: 3.4
Classifier: Programming Language :: Python :: 3.5
Classifier: Programming Language :: Python :: 3.6
Classifier: Programming Language :: Python :: 3.7
Requires-Dist: bitstring
Requires-Dist: cryptography
Requires-Dist: protobuf
